{
    "dir": "ltr",
    "resources": {
        "common-close": "Zamknij",
        "common-save": "Zapisz",
        "common-play": "Odtwórz",
        "common-resume": "Wznów",
        "english": "Angielski",
        "polish": "Polski",
        "login-title": "Zaloguj się",
        "login-password-label": "Hasło",
        "login-password-error": "Hasło musi zawierać od 8 do 20 znaków",
        "login-email-label": "E-mail",
        "login-email-error": "Ustaw poprawny adres e-mail, np. ja@adresemail.com",
        "login-button": "Zaloguj się",
        "carousel-go-to-details": "Kliknij, aby przejść do szczegółów.",
        "carousel-more": "Więcej",
        "carousel-no-title": "Brak tytułu",
        "details-screen-play-description-section-a11y-hint": "Opis filmu",
        "details-screen-no-available": "To wideo nie jest dostępne w Twoim planie.",
        "profile-title": "Wybierz profil użytkownika",
        "profile-add-new": "Dodaj nowy profil",
        "add-profile-title": "Dodaj nowy profil",
        "add-profile-choose-avatar": "Wybierz awatar",
        "add-profile-add-name": "Dodaj nazwę",
        "add-profile-form-name-label": "Nazwa",
        "add-profile-form-name-error": "Nazwa musi zawierać od 2 do 20 znaków",
        "add-profile-text-of": "z",
        "settings": "Ustawienia",
        "settings-app-version": "Wersja aplikacji",
        "settings-theme": "Motyw",
        "settings-profile": "Profil",
        "settings-language": "Język",
        "settings-current-locale": "Bieżący język",
        "settings-change-language": "Zmień język",
        "light": "Jasny",
        "dark": "Ciemny",
        "settings-log-out": "Wyloguj się",
        "video-player-caption-placeholder-na": "nd.",
        "video-player-no-captions": "Bez napisów",
        "video-player-switch-text-track-to": "Przełącz tekst na",
        "loading": "Ładowanie",
        "favorites": "Ulubione",
        "favorites-search-team": "Wyszukaj drużynę",
        "favorites-search-team-input": "Hasło wyszukiwania",
        "favorites-sort": "Sortuj",
        "favorites-sort-ascending": "Sortuj drużyny rosnąco",
        "favorites-sort-descending": "Sortuj drużyny malejąco",
        "favorites-sort-favorites": "Sortuj drużyny według ulubionych",
        "favorites-options-list": "Lista ulubionych",
        "progress-bar-a11y-label-indeterminate": "Nieokreślony postęp",
        "avatar-a11y-label": "<placeholder> awatar",
        "select-user-profile-screen-a11y-hint-click-to-log-in-as": "Kliknij, aby zalogować się jako {profileName}.",
        "a11y-hint-direction-left": "w lewo",
        "a11y-hint-direction-right": "w prawo",
        "a11y-hint-direction-up": "w górę",
        "a11y-hint-direction-down": "w dół",
        "a11y-hint-use-direction-select-item": "Użyj strzałki {direction}, aby wybrać {item}.",
        "menu-wrapper-a11y-label-menu-sentence-prefix": "Menu aplikacji,",
        "menu-wrapper-a11y-label-menu-name": "Menu aplikacji",
        "menu-wrapper-a11y-label-profile-avatar": "Awatar profilu",
        "menu-wrapper-a11y-hint-profile-avatar": "Kliknij, aby przejść do ekranu wyboru profilu.",
        "close-menu-button-a11y-label": "Zamknij menu aplikacji",
        "menu-item-use-direction-to-go-to-a11y-label": "Użyj strzałki {direction}, aby wybrać: {destination}.",
        "a11y-hint-there-is-an-item-to-the-side": "Element znajduje się {direction}.",
        "a11y-hint-there-is-an-item-below": "Poniżej znajduje się element.",
        "a11y-hint-there-is-an-item-above": "Powyżej znajduje się element.",
        "carousel-item-a11y-label": "„{item}” w grupie „{group}”.",
        "carousel-item-without-title-a11y-label": "Film bez nazwy",
        "settings-screen-a11y-theme-section-hint": "Wybór motywu",
        "settings-screen-a11y-label-theme-variant": "Motyw {themeName}",
        "settings-screen-a11y-label-theme-variant-hint": "Kliknij, aby zmienić motyw na {themeName}.",
        "a11y-hint-there-is-a-movie-list-above": "Powyżej znajduje się lista filmów.",
        "a11y-hint-there-is-a-movie-list-below": "Poniżej znajduje się lista filmów.",
        "menu-wrapper-item-home-label": "Strona główna",
        "menu-wrapper-item-settings-label": "Ustawienia",
        "login-title-form": "Formularz logowania",
        "email-field-a11y-label": "Pole adresu e-mail. Wartość: {email}"
    }
}